{
  "DRAMP ID": "SPADE_UN_12156",
  "total": 7.83,
  "category": "Good",
  "scores": {
    "efficacy": 7.0,
    "selectivity": 9.0,
    "stability": 5.0,
    "synthesis": 11.1,
    "novelty": 10.0
  },
  "weighted_scores": {
    "efficacy": 2.45,
    "selectivity": 2.25,
    "stability": 1.0,
    "synthesis": 1.33,
    "novelty": 0.8
  },
  "weights": {
    "efficacy": 0.35,
    "selectivity": 0.25,
    "stability": 0.2,
    "synthesis": 0.12,
    "novelty": 0.08
  },
  "features": {
    "hydrophobic_count": 4,
    "hydrophobic_ratio": 0.5714285714285714,
    "hydrophilic_count": 0,
    "hydrophilic_ratio": 0.0,
    "positive_count": 3,
    "positive_ratio": 0.42857142857142855,
    "negative_count": 0,
    "negative_ratio": 0.0,
    "aromatic_count": 1,
    "aromatic_ratio": 0.14285714285714285,
    "cysteine_count": 0,
    "cysteine_ratio": 0.0,
    "proline_count": 0,
    "proline_ratio": 0.0,
    "glycine_count": 0,
    "glycine_ratio": 0.0,
    "net_charge": 3,
    "hydrophobicity": 0.5714285714285714,
    "amphipathicity": 0.0,
    "aromaticity": 0.14285714285714285,
    "cys_bonds_potential": 0,
    "flexibility": 0
  },
  "details": {
    "efficacy": {
      "mic_data": [],
      "predicted_score": 10.0,
      "charge_score": 10.0,
      "hydrophobicity_score": 10.0,
      "length_factor": 0.7,
      "final_score": 7.0
    },
    "selectivity": {
      "hemolysis_data": null,
      "predicted_selectivity": 9.0,
      "hydrophobicity_penalty": 0,
      "charge_bonus": 2.0,
      "diversity_bonus": 0.0,
      "final_score": 9.0
    },
    "stability": {
      "disulfide_bonds": 0,
      "disulfide_bonus": 0,
      "proline_bonus": 0,
      "glycine_penalty": 0,
      "final_score": 5.0
    },
    "synthesis": {
      "length": 7,
      "length_score": 10.0,
      "rare_amino_acids": 1,
      "rare_penalty": 0.5,
      "unique_amino_acids": 4,
      "repetition_bonus": 1.6,
      "disulfide_penalty": 0,
      "final_score": 11.1
    },
    "novelty": {
      "max_similarity": 0,
      "avg_similarity": 0,
      "novelty_from_similarity": 10.0,
      "unique_activities": [
        "antibacterial"
      ],
      "multifunctional_bonus": 0.5,
      "composition_entropy": 1.8423709931771084,
      "composition_bonus": 0.8529495338782909,
      "final_score": 10.0
    }
  },
  "target_organisms": {},
  "scoring_version": "2.0",
  "timestamp": "2025-07-09T14:00:04.354676"
}